vaultarq/__init__.py
vaultarq/vaultarq.py
vaultarq-0.1.11.dist-info/METADATA
vaultarq-0.1.11.dist-info/WHEEL
vaultarq-0.1.11.dist-info/top_level.txt
vaultarq-0.1.11.dist-info/RECORD
