Metadata-Version: 2.4
Name: vaultarq
Version: 0.1.11
Summary: Python SDK for Vaultarq - The developer-first, invisible secrets manager
Home-page: https://github.com/Vaultarq/vaultarq
Author: Dedan Okware
Author-email: softengdedan@gmail.com
Project-URL: Bug Tracker, https://github.com/Vaultarq/vaultarq/issues
Keywords: secrets,environment,env,secrets-management,security
Classifier: Programming Language :: Python :: 3
Classifier: Programming Language :: Python :: 3.7
Classifier: Programming Language :: Python :: 3.8
Classifier: Programming Language :: Python :: 3.9
Classifier: Programming Language :: Python :: 3.10
Classifier: License :: OSI Approved :: MIT License
Classifier: Operating System :: OS Independent
Classifier: Development Status :: 4 - Beta
Classifier: Intended Audience :: Developers
Classifier: Topic :: Security
Classifier: Topic :: Software Development
Requires-Python: >=3.7
Dynamic: author
Dynamic: author-email
Dynamic: classifier
Dynamic: description
Dynamic: description-content-type
Dynamic: home-page
Dynamic: keywords
Dynamic: project-url
Dynamic: requires-python
Dynamic: summary
